python/tests/tb.v
/*
    This is a simple Verilog testbench for the basic module.
*/

module tb;

    reg clk;
    reg [7:0] cycle;
    initial begin
        clk = 1;
        cycle = 0;
    end

    always #1 clk = ~clk;
    always @(posedge clk) begin
        cycle = cycle + 1;
    end

    // Run for 30 clock cycles
    initial begin
        #30 $finish;
    end

    initial begin
        $dumpfile("basic.vcd");
        $dumpvars(0, tb);
    end
endmodule

python/tests/basic.vcd
$date
	Tue Feb  3 11:34:09 2026
$end
$version
	Icarus Verilog
$end
$timescale
	1s
$end
$scope module tb $end
$var reg 1 ! clk $end
$var reg 8 " cycle [7:0] $end
$upscope $end
$enddefinitions $end
$comment Show the parameter values. $end
$dumpall
$end
#0
$dumpvars
b0 "
1!
$end
#1
0!
#2
b1 "
1!
#3
0!
#4
b10 "
1!
#5
0!
#6
b11 "
1!
#7
0!
#8
b100 "
1!
#9
0!
#10
b101 "
1!
#11
0!
#12
b110 "
1!
#13
0!
#14
b111 "
1!
#15
0!
#16
b1000 "
1!
#17
0!
#18
b1001 "
1!
#19
0!
#20
b1010 "
1!
#21
0!
#22
b1011 "
1!
#23
0!
#24
b1100 "
1!
#25
0!
#26
b1101 "
1!
#27
0!
#28
b1110 "
1!
#29
0!
#30
b1111 "
1!
